posmatch/__init__.py
posmatch/core.py
posmatch-0.8.1.dist-info/LICENSE
posmatch-0.8.1.dist-info/METADATA
posmatch-0.8.1.dist-info/WHEEL
posmatch-0.8.1.dist-info/RECORD
