Metadata-Version: 2.1
Name: posmatch
Version: 0.8.1
Summary: Positional sub-pattern matching for custom classes.
Home-page: https://github.com/mportesdev/posmatch
License: MIT
Author: Michal Porteš
Author-email: michalportes1@gmail.com
Requires-Python: >=3.10,<4.0
Classifier: Development Status :: 4 - Beta
Classifier: License :: OSI Approved :: MIT License
Classifier: Operating System :: OS Independent
Classifier: Programming Language :: Python :: 3
Classifier: Programming Language :: Python :: 3.10
Classifier: Programming Language :: Python :: 3.11
Classifier: Programming Language :: Python :: 3.12
Classifier: Programming Language :: Python :: 3.13
Classifier: Topic :: Software Development :: Libraries :: Python Modules
